netpiko/__init__.py
netpiko-0.0.1.dist-info/LICENSE
netpiko-0.0.1.dist-info/METADATA
netpiko-0.0.1.dist-info/WHEEL
netpiko-0.0.1.dist-info/top_level.txt
netpiko-0.0.1.dist-info/RECORD
